kalshi_py/__init__.py
kalshi_py/api/__init__.py
kalshi_py/api/api_keys/__init__.py
kalshi_py/api/api_keys/create_api_key.py
kalshi_py/api/api_keys/delete_api_key.py
kalshi_py/api/api_keys/generate_api_key.py
kalshi_py/api/api_keys/get_api_keys.py
kalshi_py/api/collection/__init__.py
kalshi_py/api/collection/create_market_in_multivariate_event_collection.py
kalshi_py/api/collection/get_multivariate_event_collection.py
kalshi_py/api/collection/get_multivariate_event_collection_lookup_history.py
kalshi_py/api/collection/get_multivariate_event_collections.py
kalshi_py/api/collection/lookup_tickers_for_market_in_multivariate_event_collection.py
kalshi_py/api/communications/__init__.py
kalshi_py/api/communications/accept_quote.py
kalshi_py/api/communications/confirm_quote.py
kalshi_py/api/communications/create_quote.py
kalshi_py/api/communications/create_rfq.py
kalshi_py/api/communications/delete_quote.py
kalshi_py/api/communications/delete_rfq.py
kalshi_py/api/communications/get_communications_id.py
kalshi_py/api/communications/get_quote.py
kalshi_py/api/communications/get_quotes.py
kalshi_py/api/communications/get_rf_qs.py
kalshi_py/api/communications/get_rfq.py
kalshi_py/api/default/__init__.py
kalshi_py/api/default/get_exchange_announcements.py
kalshi_py/api/default/get_exchange_schedule.py
kalshi_py/api/default/get_exchange_status.py
kalshi_py/api/default/get_user_data_timestamp.py
kalshi_py/api/market/__init__.py
kalshi_py/api/market/get_event.py
kalshi_py/api/market/get_event_metadata.py
kalshi_py/api/market/get_events.py
kalshi_py/api/market/get_market.py
kalshi_py/api/market/get_market_candlesticks.py
kalshi_py/api/market/get_market_orderbook.py
kalshi_py/api/market/get_markets.py
kalshi_py/api/market/get_series.py
kalshi_py/api/market/get_series_list.py
kalshi_py/api/market/get_trades.py
kalshi_py/api/milestone/__init__.py
kalshi_py/api/milestone/get_milestone.py
kalshi_py/api/milestone/get_milestones.py
kalshi_py/api/portfolio/__init__.py
kalshi_py-2.0.6.6.dist-info/WHEEL
kalshi_py-2.0.6.6.dist-info/entry_points.txt
kalshi_py-2.0.6.6.dist-info/METADATA
kalshi_py-2.0.6.6.dist-info/RECORD
