Metadata-Version: 2.3
Name: kalshi-py
Version: 2.0.6.6
Summary: A client library for accessing Kalshi Trade API
Requires-Dist: httpx>=0.23.0,<0.29.0
Requires-Dist: attrs>=22.2.0
Requires-Dist: python-dateutil>=2.8.0,<3
Requires-Dist: cryptography>=41.0.0
Requires-Dist: mkdocs-material>=9.6.16
Requires-Python: ~=3.9
